flat_styled_jupyter_notebooks/__init__.py
flat_styled_jupyter_notebooks/flat_styled_jupyter_notebooks.py
flat_styled_jupyter_notebooks-0.2.0.dist-info/AUTHORS.rst
flat_styled_jupyter_notebooks-0.2.0.dist-info/LICENSE
flat_styled_jupyter_notebooks-0.2.0.dist-info/METADATA
flat_styled_jupyter_notebooks-0.2.0.dist-info/WHEEL
flat_styled_jupyter_notebooks-0.2.0.dist-info/top_level.txt
flat_styled_jupyter_notebooks-0.2.0.dist-info/RECORD
